sireader.py
sireader-1.1.3.dist-info/COPYING
sireader-1.1.3.dist-info/METADATA
sireader-1.1.3.dist-info/WHEEL
sireader-1.1.3.dist-info/top_level.txt
sireader-1.1.3.dist-info/RECORD
