Metadata-Version: 2.1
Name: sireader
Version: 1.1.3
Summary: Python module to communicate with SportIdent main stations
Home-page: http://bosco.durcheinandertal.ch/
Author: Gaudenz Steinlin
Author-email: gaudenz@durcheinandertal.ch
License: GPLv3+
Keywords: sportident orienteering bosco
Platform: UNKNOWN
Classifier: Development Status :: 5 - Production/Stable
Classifier: Intended Audience :: Developers
Classifier: Topic :: System :: Hardware :: Hardware Drivers
Classifier: License :: OSI Approved :: GNU General Public License v3 or later (GPLv3+)
Classifier: Programming Language :: Python :: 2
Classifier: Programming Language :: Python :: 2.6
Classifier: Programming Language :: Python :: 2.7
Classifier: Programming Language :: Python :: 3
Classifier: Programming Language :: Python :: 3.2
Classifier: Programming Language :: Python :: 3.3
Classifier: Programming Language :: Python :: 3.4
Requires-Dist: pyserial
Requires-Dist: six
